adt/__init__.py
adt/core.py
tests/__init__.py
tests/test_adt.py
tests/test_multimethod.py
algebraic_data_type-0.0.4.dist-info/LICENSE.md
algebraic_data_type-0.0.4.dist-info/METADATA
algebraic_data_type-0.0.4.dist-info/WHEEL
algebraic_data_type-0.0.4.dist-info/top_level.txt
algebraic_data_type-0.0.4.dist-info/RECORD
