Metadata-Version: 2.1
Name: algebraic-data-type
Version: 0.0.4
Summary: Algebraic data type and pattern matching
Home-page: https://github.com/catethos/adt
Author: Caleb Foong
Author-email: catethos@gmail.com
License: The MIT License
Platform: UNKNOWN
Classifier: Programming Language :: Python :: 3
Classifier: License :: OSI Approved :: MIT License
Classifier: Operating System :: OS Independent
Requires-Python: >=3.7
Requires-Dist: pampy
